LICENSE
MANIFEST.in
README.md
islykill.py
setup.py
py_islykill.egg-info/PKG-INFO
py_islykill.egg-info/SOURCES.txt
py_islykill.egg-info/dependency_links.txt
py_islykill.egg-info/top_level.txt