Metadata-Version: 1.0
Name: py-islykill
Version: 0.1
Summary: A simple python client for the Icelandic government authentication service Íslykill (www.islykill.is)
Home-page: http://github.com/overcastsoftware/py-islykill
Author: Overcast Software - Sævar Öfjörð Magnússon
Author-email: saevar@overcast.io
License: MIT
Platform: any
Classifier: Development Status :: 4 - Beta
Classifier: Intended Audience :: Developers
Classifier: License :: OSI Approved :: MIT License
Classifier: Operating System :: OS Independent
Classifier: Programming Language :: Python
Classifier: Topic :: Software Development :: Libraries :: Python Modules
